{
  "ranked_records": [
    {
      "code": "840043172",
      "nickname": "[ΛF] Stussy <3",
      "level": 1710,
      "bounty": "1301850000",
      "rank": 1,
      "character_id": 14619,
      "rescue_count": 10,
      "battle_count": 169,
      "kizuna_battle_point": 105362654536
    },
    {
      "code": "603899358",
      "nickname": "RM",
      "level": 368,
      "bounty": "15150000",
      "rank": 2,
      "character_id": 14452,
      "rescue_count": 0,
      "battle_count": 189,
      "kizuna_battle_point": 61321952604
    },
    {
      "code": "645209536",
      "nickname": "  【喝】 용병",
      "level": 293,
      "bounty": "19750000",
      "rank": 3,
      "character_id": 14452,
      "rescue_count": 0,
      "battle_count": 177,
      "kizuna_battle_point": 27227585056
    },
    {
      "code": "397409929",
      "nickname": "검은이무 노가을성",
      "level": 304,
      "bounty": "13850000",
      "rank": 4,
      "character_id": 13969,
      "rescue_count": 5,
      "battle_count": 179,
      "kizuna_battle_point": 20771771648
    },
    {
      "code": "072933804",
      "nickname": "생로랑",
      "level": 251,
      "bounty": "103850000",
      "rank": 5,
      "character_id": 14619,
      "rescue_count": 22,
      "battle_count": 163,
      "kizuna_battle_point": 13841039345
    },
    {
      "code": "150153915",
      "nickname": "바스코",
      "level": 449,
      "bounty": "21340000",
      "rank": 6,
      "character_id": 14619,
      "rescue_count": 8,
      "battle_count": 159,
      "kizuna_battle_point": 8055539293
    },
    {
      "code": "261203719",
      "nickname": "ヘイヴァ",
      "level": 306,
      "bounty": "19100000",
      "rank": 7,
      "character_id": 1535,
      "rescue_count": 2,
      "battle_count": 156,
      "kizuna_battle_point": 6575688144
    },
    {
      "code": "230392626",
      "nickname": "ZEnki",
      "level": 205,
      "bounty": "21250000",
      "rank": 8,
      "character_id": 14619,
      "rescue_count": 5,
      "battle_count": 150,
      "kizuna_battle_point": 5367688823
    },
    {
      "code": "632477755",
      "nickname": "PewPewKing",
      "level": 519,
      "bounty": "281650000",
      "rank": 9,
      "character_id": 14619,
      "rescue_count": 23,
      "battle_count": 97,
      "kizuna_battle_point": 4094943450
    },
    {
      "code": "340641923",
      "nickname": "⚡️하돌⚡️",
      "level": 375,
      "bounty": "129950000",
      "rank": 10,
      "character_id": 13472,
      "rescue_count": 42,
      "battle_count": 139,
      "kizuna_battle_point": 2383224274
    },
    {
      "code": "099209830",
      "nickname": "쏘야쭈야 해적단",
      "level": 343,
      "bounty": "20100000",
      "rank": 11,
      "character_id": 14619,
      "rescue_count": 3,
      "battle_count": 141,
      "kizuna_battle_point": 2383223057
    },
    {
      "code": "320543931",
      "nickname": "qpLAUqp",
      "level": 278,
      "bounty": "195200000",
      "rank": 12,
      "character_id": 14619,
      "rescue_count": 10,
      "battle_count": 132,
      "kizuna_battle_point": 1132165112
    },
    {
      "code": "130295085",
      "nickname": "삼삼",
      "level": 316,
      "bounty": "19560000",
      "rank": 13,
      "character_id": 14608,
      "rescue_count": 18,
      "battle_count": 125,
      "kizuna_battle_point": 988853955
    },
    {
      "code": "504890376",
      "nickname": "[GT] Espen223",
      "level": 869,
      "bounty": "590410000",
      "rank": 14,
      "character_id": 14619,
      "rescue_count": 6,
      "battle_count": 105,
      "kizuna_battle_point": 807166679
    },
    {
      "code": "125623764",
      "nickname": "다오니",
      "level": 1227,
      "bounty": "493410000",
      "rank": 15,
      "character_id": 12662,
      "rescue_count": 8,
      "battle_count": 122,
      "kizuna_battle_point": 658856965
    },
    {
      "code": "497834271",
      "nickname": "꧁⚔️Chimaera⚔️꧂",
      "level": 214,
      "bounty": "16200000",
      "rank": 16,
      "character_id": 14619,
      "rescue_count": 12,
      "battle_count": 120,
      "kizuna_battle_point": 615744525
    },
    {
      "code": "996720342",
      "nickname": "김첨지네설렁탕집",
      "level": 300,
      "bounty": "25770000",
      "rank": 17,
      "character_id": 14619,
      "rescue_count": 38,
      "battle_count": 119,
      "kizuna_battle_point": 502606820
    },
    {
      "code": "428259306",
      "nickname": "쏘쏘야",
      "level": 211,
      "bounty": "12500000",
      "rank": 18,
      "character_id": 14619,
      "rescue_count": 0,
      "battle_count": 114,
      "kizuna_battle_point": 502598192
    },
    {
      "code": "065943225",
      "nickname": "Weng",
      "level": 761,
      "bounty": "127350000",
      "rank": 19,
      "character_id": 10600,
      "rescue_count": 2,
      "battle_count": 116,
      "kizuna_battle_point": 410238385
    },
    {
      "code": "803959179",
      "nickname": "os",
      "level": 292,
      "bounty": "21200000",
      "rank": 20,
      "character_id": 14619,
      "rescue_count": 1,
      "battle_count": 110,
      "kizuna_battle_point": 383389120
    },
    {
      "code": "198724317",
      "nickname": "GachaJunkies",
      "level": 286,
      "bounty": "20100000",
      "rank": 21,
      "character_id": 14608,
      "rescue_count": 1,
      "battle_count": 110,
      "kizuna_battle_point": 358297877
    },
    {
      "code": "691533188",
      "nickname": "(라프텔)블루",
      "level": 1047,
      "bounty": "872125000",
      "rank": 22,
      "character_id": 14619,
      "rescue_count": 32,
      "battle_count": 94,
      "kizuna_battle_point": 292445090
    },
    {
      "code": "692240388",
      "nickname": "츠키무라 테마리",
      "level": 244,
      "bounty": "5200000",
      "rank": 23,
      "character_id": 14619,
      "rescue_count": 0,
      "battle_count": 105,
      "kizuna_battle_point": 273301957
    },
    {
      "code": "080303934",
      "nickname": "Callacops",
      "level": 330,
      "bounty": "161400000",
      "rank": 23,
      "character_id": 14620,
      "rescue_count": 10,
      "battle_count": 105,
      "kizuna_battle_point": 273301957
    },
    {
      "code": "974830787",
      "nickname": "시퍼",
      "level": 283,
      "bounty": "21100000",
      "rank": 25,
      "character_id": 14619,
      "rescue_count": 28,
      "battle_count": 101,
      "kizuna_battle_point": 194812830
    },
    {
      "code": "230191593",
      "nickname": "이유",
      "level": 333,
      "bounty": "26450000",
      "rank": 26,
      "character_id": 13969,
      "rescue_count": 47,
      "battle_count": 104,
      "kizuna_battle_point": 194811330
    },
    {
      "code": "304902790",
      "nickname": "모자 toMMy D",
      "level": 181,
      "bounty": "14100000",
      "rank": 27,
      "character_id": 13358,
      "rescue_count": 6,
      "battle_count": 105,
      "kizuna_battle_point": 182056982
    },
    {
      "code": "524593323",
      "nickname": "Kayden ",
      "level": 306,
      "bounty": "115710000",
      "rank": 28,
      "character_id": 14619,
      "rescue_count": 2,
      "battle_count": 75,
      "kizuna_battle_point": 170135570
    },
    {
      "code": "079234893",
      "nickname": "골.D.로저",
      "level": 249,
      "bounty": "33530000",
      "rank": 29,
      "character_id": 14619,
      "rescue_count": 31,
      "battle_count": 46,
      "kizuna_battle_point": 170134070
    },
    {
      "code": "932991656",
      "nickname": "딸둘아빠",
      "level": 288,
      "bounty": "21100000",
      "rank": 29,
      "character_id": 14619,
      "rescue_count": 23,
      "battle_count": 98,
      "kizuna_battle_point": 170134070
    },
    {
      "code": "045932778",
      "nickname": "DSG.คำแก้ว",
      "level": 213,
      "bounty": "111350000",
      "rank": 31,
      "character_id": 14608,
      "rescue_count": 6,
      "battle_count": 135,
      "kizuna_battle_point": 159216042
    },
    {
      "code": "722529309",
      "nickname": "tru CHUMP.",
      "level": 304,
      "bounty": "14250000",
      "rank": 32,
      "character_id": 13361,
      "rescue_count": 59,
      "battle_count": 97,
      "kizuna_battle_point": 158992592
    },
    {
      "code": "144003919",
      "nickname": "armaster",
      "level": 242,
      "bounty": "19180000",
      "rank": 33,
      "character_id": 14619,
      "rescue_count": 5,
      "battle_count": 102,
      "kizuna_battle_point": 138851732
    },
    {
      "code": "539090839",
      "nickname": "석나간 윤열",
      "level": 372,
      "bounty": "58550000",
      "rank": 34,
      "character_id": 14122,
      "rescue_count": 14,
      "battle_count": 99,
      "kizuna_battle_point": 138848597
    },
    {
      "code": "576332528",
      "nickname": "Schwäggo ",
      "level": 559,
      "bounty": "32850000",
      "rank": 35,
      "character_id": 14619,
      "rescue_count": 16,
      "battle_count": 99,
      "kizuna_battle_point": 129755332
    },
    {
      "code": "072957223",
      "nickname": "Alaska Big Worm",
      "level": 207,
      "bounty": "16750000",
      "rank": 36,
      "character_id": 14608,
      "rescue_count": 16,
      "battle_count": 94,
      "kizuna_battle_point": 129753832
    },
    {
      "code": "423637938",
      "nickname": "nooy4289",
      "level": 700,
      "bounty": "316935000",
      "rank": 37,
      "character_id": 14619,
      "rescue_count": 7,
      "battle_count": 98,
      "kizuna_battle_point": 121254082
    },
    {
      "code": "739110997",
      "nickname": "ZEUS☠️",
      "level": 475,
      "bounty": "235650000",
      "rank": 38,
      "character_id": 13414,
      "rescue_count": 16,
      "battle_count": 97,
      "kizuna_battle_point": 121254052
    },
    {
      "code": "254783307",
      "nickname": "The Hyena",
      "level": 710,
      "bounty": "231355000",
      "rank": 38,
      "character_id": 14012,
      "rescue_count": 7,
      "battle_count": 97,
      "kizuna_battle_point": 121254052
    },
    {
      "code": "254836831",
      "nickname": "럭키가이",
      "level": 1707,
      "bounty": "1256650000",
      "rank": 40,
      "character_id": 14619,
      "rescue_count": 1,
      "battle_count": 96,
      "kizuna_battle_point": 113310332
    },
    {
      "code": "873185883",
      "nickname": "XxLuffyxX",
      "level": 637,
      "bounty": "720385000",
      "rank": 41,
      "character_id": 14411,
      "rescue_count": 12,
      "battle_count": 44,
      "kizuna_battle_point": 105894923
    },
    {
      "code": "561353122",
      "nickname": "™Bro☠오뎅",
      "level": 1199,
      "bounty": "737930000",
      "rank": 42,
      "character_id": 12760,
      "rescue_count": 14,
      "battle_count": 51,
      "kizuna_battle_point": 105886295
    },
    {
      "code": "493780511",
      "nickname": "시팍",
      "level": 301,
      "bounty": "18250000",
      "rank": 42,
      "character_id": 14619,
      "rescue_count": 2,
      "battle_count": 95,
      "kizuna_battle_point": 105886295
    },
    {
      "code": "029932668",
      "nickname": "사마귀",
      "level": 297,
      "bounty": "22480000",
      "rank": 42,
      "character_id": 14619,
      "rescue_count": 27,
      "battle_count": 95,
      "kizuna_battle_point": 105886295
    },
    {
      "code": "342478825",
      "nickname": "Galy",
      "level": 558,
      "bounty": "175825000",
      "rank": 45,
      "character_id": 13904,
      "rescue_count": 13,
      "battle_count": 94,
      "kizuna_battle_point": 98947942
    },
    {
      "code": "962420732",
      "nickname": "밀짚",
      "level": 288,
      "bounty": "21600000",
      "rank": 46,
      "character_id": 14619,
      "rescue_count": 4,
      "battle_count": 93,
      "kizuna_battle_point": 92463500
    },
    {
      "code": "436293788",
      "nickname": "popson2",
      "level": 223,
      "bounty": "33100000",
      "rank": 47,
      "character_id": 13358,
      "rescue_count": 1,
      "battle_count": 90,
      "kizuna_battle_point": 80742646
    },
    {
      "code": "327928993",
      "nickname": "Killuaz",
      "level": 329,
      "bounty": "35140000",
      "rank": 48,
      "character_id": 14608,
      "rescue_count": 1,
      "battle_count": 71,
      "kizuna_battle_point": 80739511
    },
    {
      "code": "643579881",
      "nickname": "Sheogorath97",
      "level": 291,
      "bounty": "64240000",
      "rank": 49,
      "character_id": 14573,
      "rescue_count": 6,
      "battle_count": 92,
      "kizuna_battle_point": 70502460
    },
    {
      "code": "325970755",
      "nickname": "Sole",
      "level": 233,
      "bounty": "25750000",
      "rank": 50,
      "character_id": 14608,
      "rescue_count": 10,
      "battle_count": 90,
      "kizuna_battle_point": 65877537
    },
    {
      "code": "032323686",
      "nickname": "올블루",
      "level": 405,
      "bounty": "182450000",
      "rank": 51,
      "character_id": 14619,
      "rescue_count": 20,
      "battle_count": 52,
      "kizuna_battle_point": 65876007
    },
    {
      "code": "375241282",
      "nickname": "Loki’s Crew",
      "level": 232,
      "bounty": "19765000",
      "rank": 52,
      "character_id": 14619,
      "rescue_count": 24,
      "battle_count": 98,
      "kizuna_battle_point": 61568446
    },
    {
      "code": "800923806",
      "nickname": "(βvˢ⚜️) DayToNa007",
      "level": 698,
      "bounty": "869700000",
      "rank": 53,
      "character_id": 12760,
      "rescue_count": 13,
      "battle_count": 83,
      "kizuna_battle_point": 61555149
    },
    {
      "code": "770490433",
      "nickname": "[E10] Pandake ☯︎",
      "level": 260,
      "bounty": "13200000",
      "rank": 53,
      "character_id": 12614,
      "rescue_count": 0,
      "battle_count": 83,
      "kizuna_battle_point": 61555149
    },
    {
      "code": "537062613",
      "nickname": "Ichiekuro1",
      "level": 378,
      "bounty": "114670000",
      "rank": 55,
      "character_id": 13904,
      "rescue_count": 3,
      "battle_count": 119,
      "kizuna_battle_point": 58738234
    },
    {
      "code": "210397559",
      "nickname": "밀짚모자 일당11",
      "level": 278,
      "bounty": "21100000",
      "rank": 56,
      "character_id": 13052,
      "rescue_count": 2,
      "battle_count": 86,
      "kizuna_battle_point": 57516964
    },
    {
      "code": "739120969",
      "nickname": "Dazai Villains",
      "level": 315,
      "bounty": "161550000",
      "rank": 56,
      "character_id": 13908,
      "rescue_count": 0,
      "battle_count": 82,
      "kizuna_battle_point": 57516964
    },
    {
      "code": "300683453",
      "nickname": "☠️P✘M☠️-윤아",
      "level": 4081,
      "bounty": "1142275000",
      "rank": 56,
      "character_id": 14619,
      "rescue_count": 33,
      "battle_count": 86,
      "kizuna_battle_point": 57516964
    },
    {
      "code": "001332624",
      "nickname": "avgermany",
      "level": 545,
      "bounty": "122150000",
      "rank": 59,
      "character_id": 14619,
      "rescue_count": 21,
      "battle_count": 69,
      "kizuna_battle_point": 53742960
    },
    {
      "code": "178263299",
      "nickname": "아래적",
      "level": 539,
      "bounty": "123790000",
      "rank": 59,
      "character_id": 14619,
      "rescue_count": 23,
      "battle_count": 41,
      "kizuna_battle_point": 53742960
    },
    {
      "code": "031923500",
      "nickname": "골D.로져",
      "level": 154,
      "bounty": "13500000",
      "rank": 59,
      "character_id": 14608,
      "rescue_count": 8,
      "battle_count": 85,
      "kizuna_battle_point": 53742960
    },
    {
      "code": "896436130",
      "nickname": "Smoove",
      "level": 404,
      "bounty": "44370000",
      "rank": 62,
      "character_id": 13706,
      "rescue_count": 1,
      "battle_count": 112,
      "kizuna_battle_point": 51279876
    },
    {
      "code": "680890350",
      "nickname": "O ᶘ ᵒᴥᵒᶅ G ",
      "level": 1057,
      "bounty": "867825000",
      "rank": 63,
      "character_id": 14619,
      "rescue_count": 1,
      "battle_count": 76,
      "kizuna_battle_point": 50215853
    },
    {
      "code": "762359985",
      "nickname": "Storm Returns",
      "level": 355,
      "bounty": "59600000",
      "rank": 64,
      "character_id": 14619,
      "rescue_count": 2,
      "battle_count": 54,
      "kizuna_battle_point": 43838779
    },
    {
      "code": "438894248",
      "nickname": "Fans Pak Purbaya",
      "level": 237,
      "bounty": "21250000",
      "rank": 64,
      "character_id": 14619,
      "rescue_count": 24,
      "battle_count": 82,
      "kizuna_battle_point": 43838779
    },
    {
      "code": "037927356",
      "nickname": "[GT] Wyne",
      "level": 1683,
      "bounty": "1089225000",
      "rank": 64,
      "character_id": 13472,
      "rescue_count": 42,
      "battle_count": 82,
      "kizuna_battle_point": 43838779
    },
    {
      "code": "398710389",
      "nickname": "Dead D. King ",
      "level": 868,
      "bounty": "431975000",
      "rank": 64,
      "character_id": 14619,
      "rescue_count": 5,
      "battle_count": 42,
      "kizuna_battle_point": 43838779
    },
    {
      "code": "436748394",
      "nickname": "┢┦aΡｐy ✄ ✪.◕‿◕.",
      "level": 189,
      "bounty": "74350000",
      "rank": 68,
      "character_id": 14411,
      "rescue_count": 21,
      "battle_count": 81,
      "kizuna_battle_point": 40959609
    },
    {
      "code": "932270831",
      "nickname": "밀짚모자일당",
      "level": 335,
      "bounty": "21150000",
      "rank": 68,
      "character_id": 14606,
      "rescue_count": 25,
      "battle_count": 81,
      "kizuna_battle_point": 40959609
    },
    {
      "code": "452143046",
      "nickname": "GGGori",
      "level": 815,
      "bounty": "666850000",
      "rank": 70,
      "character_id": 14619,
      "rescue_count": 4,
      "battle_count": 56,
      "kizuna_battle_point": 38268796
    },
    {
      "code": "813423239",
      "nickname": "Weeaboo Pirates",
      "level": 609,
      "bounty": "512135000",
      "rank": 70,
      "character_id": 14606,
      "rescue_count": 0,
      "battle_count": 52,
      "kizuna_battle_point": 38268796
    },
    {
      "code": "798983092",
      "nickname": "Colonel Diqsuk",
      "level": 278,
      "bounty": "17500000",
      "rank": 70,
      "character_id": 14619,
      "rescue_count": 3,
      "battle_count": 76,
      "kizuna_battle_point": 38268796
    },
    {
      "code": "966930857",
      "nickname": "☆ahchang☆",
      "level": 300,
      "bounty": "18600000",
      "rank": 70,
      "character_id": 14619,
      "rescue_count": 8,
      "battle_count": 80,
      "kizuna_battle_point": 38268796
    },
    {
      "code": "280239988",
      "nickname": "아이젠 소스케",
      "level": 273,
      "bounty": "16100000",
      "rank": 70,
      "character_id": 14619,
      "rescue_count": 8,
      "battle_count": 76,
      "kizuna_battle_point": 38268796
    },
    {
      "code": "517341596",
      "nickname": "GAZA (PaP) (OPe)",
      "level": 733,
      "bounty": "455295000",
      "rank": 70,
      "character_id": 12760,
      "rescue_count": 5,
      "battle_count": 80,
      "kizuna_battle_point": 38268796
    },
    {
      "code": "894239626",
      "nickname": "EXC",
      "level": 297,
      "bounty": "16400000",
      "rank": 76,
      "character_id": 13361,
      "rescue_count": 15,
      "battle_count": 87,
      "kizuna_battle_point": 35767031
    },
    {
      "code": "649739928",
      "nickname": "br.Jinga",
      "level": 503,
      "bounty": "120790000",
      "rank": 77,
      "character_id": 14619,
      "rescue_count": 17,
      "battle_count": 79,
      "kizuna_battle_point": 35754017
    },
    {
      "code": "992064631",
      "nickname": "TRA - Procamich",
      "level": 1912,
      "bounty": "1344150000",
      "rank": 77,
      "character_id": 10153,
      "rescue_count": 33,
      "battle_count": 79,
      "kizuna_battle_point": 35754017
    },
    {
      "code": "760043243",
      "nickname": "MUGIWARA",
      "level": 606,
      "bounty": "88150000",
      "rank": 77,
      "character_id": 13472,
      "rescue_count": 13,
      "battle_count": 67,
      "kizuna_battle_point": 35754017
    },
    {
      "code": "910193104",
      "nickname": "토두",
      "level": 601,
      "bounty": "16150000",
      "rank": 80,
      "character_id": 14608,
      "rescue_count": 15,
      "battle_count": 78,
      "kizuna_battle_point": 33403757
    },
    {
      "code": "065933073",
      "nickname": "사황no.2",
      "level": 304,
      "bounty": "53950000",
      "rank": 80,
      "character_id": 14619,
      "rescue_count": 11,
      "battle_count": 74,
      "kizuna_battle_point": 33403757
    },
    {
      "code": "161633529",
      "nickname": "밀짚모자 일당들",
      "level": 266,
      "bounty": "13750000",
      "rank": 82,
      "character_id": 14619,
      "rescue_count": 25,
      "battle_count": 85,
      "kizuna_battle_point": 31220266
    },
    {
      "code": "540395618",
      "nickname": "Garp",
      "level": 370,
      "bounty": "200750000",
      "rank": 83,
      "character_id": 14606,
      "rescue_count": 0,
      "battle_count": 79,
      "kizuna_battle_point": 31208927
    },
    {
      "code": "720739876",
      "nickname": "공식카페 : CAT",
      "level": 374,
      "bounty": "14600000",
      "rank": 84,
      "character_id": 13361,
      "rescue_count": 15,
      "battle_count": 73,
      "kizuna_battle_point": 31207252
    },
    {
      "code": "341643573",
      "nickname": "가나다라마바사",
      "level": 597,
      "bounty": "357100000",
      "rank": 84,
      "character_id": 14573,
      "rescue_count": 11,
      "battle_count": 77,
      "kizuna_battle_point": 31207252
    },
    {
      "code": "836713567",
      "nickname": "홍",
      "level": 1056,
      "bounty": "363340000",
      "rank": 84,
      "character_id": 14619,
      "rescue_count": 27,
      "battle_count": 69,
      "kizuna_battle_point": 31207252
    },
    {
      "code": "754392704",
      "nickname": "Albanianking",
      "level": 214,
      "bounty": "201050000",
      "rank": 87,
      "character_id": 14573,
      "rescue_count": 1,
      "battle_count": 107,
      "kizuna_battle_point": 29836400
    },
    {
      "code": "226203349",
      "nickname": "쿠우",
      "level": 291,
      "bounty": "14000000",
      "rank": 88,
      "character_id": 14619,
      "rescue_count": 12,
      "battle_count": 76,
      "kizuna_battle_point": 29154443
    },
    {
      "code": "643523831",
      "nickname": "동그리ㅇ",
      "level": 1158,
      "bounty": "781900000",
      "rank": 89,
      "character_id": 14619,
      "rescue_count": 34,
      "battle_count": 75,
      "kizuna_battle_point": 27235930
    },
    {
      "code": "943417055",
      "nickname": "Jugo Pirates",
      "level": 388,
      "bounty": "171005000",
      "rank": 90,
      "character_id": 14571,
      "rescue_count": 15,
      "battle_count": 69,
      "kizuna_battle_point": 25444490
    },
    {
      "code": "634780688",
      "nickname": "Law Pirates",
      "level": 306,
      "bounty": "121950000",
      "rank": 91,
      "character_id": 13052,
      "rescue_count": 2,
      "battle_count": 71,
      "kizuna_battle_point": 25442957
    },
    {
      "code": "112733316",
      "nickname": "chibres mous",
      "level": 219,
      "bounty": "35995000",
      "rank": 92,
      "character_id": 14619,
      "rescue_count": 8,
      "battle_count": 30,
      "kizuna_battle_point": 25442927
    },
    {
      "code": "380263601",
      "nickname": "F2P. Starter☠",
      "level": 292,
      "bounty": "21750000",
      "rank": 92,
      "character_id": 13904,
      "rescue_count": 13,
      "battle_count": 74,
      "kizuna_battle_point": 25442927
    },
    {
      "code": "893700173",
      "nickname": "루안이네",
      "level": 573,
      "bounty": "158420000",
      "rank": 92,
      "character_id": 12662,
      "rescue_count": 46,
      "battle_count": 74,
      "kizuna_battle_point": 25442927
    },
    {
      "code": "603853823",
      "nickname": "BlackHeart Pir8ts",
      "level": 429,
      "bounty": "4200000",
      "rank": 95,
      "character_id": 12110,
      "rescue_count": 3,
      "battle_count": 108,
      "kizuna_battle_point": 24376365
    },
    {
      "code": "536761133",
      "nickname": "浪花龍虎",
      "level": 581,
      "bounty": "198865000",
      "rank": 96,
      "character_id": 13361,
      "rescue_count": 16,
      "battle_count": 104,
      "kizuna_battle_point": 24351462
    },
    {
      "code": "299110337",
      "nickname": "ZionType",
      "level": 157,
      "bounty": "250000",
      "rank": 97,
      "character_id": 14619,
      "rescue_count": 14,
      "battle_count": 63,
      "kizuna_battle_point": 23805188
    },
    {
      "code": "639742366",
      "nickname": "Raynotgay",
      "level": 304,
      "bounty": "115810000",
      "rank": 98,
      "character_id": 14606,
      "rescue_count": 8,
      "battle_count": 72,
      "kizuna_battle_point": 23772047
    },
    {
      "code": "834743393",
      "nickname": "Jojov2. ",
      "level": 182,
      "bounty": "153050000",
      "rank": 99,
      "character_id": 13703,
      "rescue_count": 0,
      "battle_count": 69,
      "kizuna_battle_point": 23767224
    },
    {
      "code": "488248356",
      "nickname": "qrx185",
      "level": 238,
      "bounty": "189200000",
      "rank": 99,
      "character_id": 14619,
      "rescue_count": 3,
      "battle_count": 69,
      "kizuna_battle_point": 23767224
    }
  ],
  "last_updated": "2025-10-25T02:29:42.500976+00:00"
}